harlequin_trino/__init__.py
harlequin_trino/adapter.py
harlequin_trino/cli_options.py
harlequin_trino/completions.py
harlequin_trino/functions.tsv
harlequin_trino/keywords.csv
harlequin_trino/py.typed
harlequin_trino-0.1.6.dist-info/LICENSE
harlequin_trino-0.1.6.dist-info/METADATA
harlequin_trino-0.1.6.dist-info/WHEEL
harlequin_trino-0.1.6.dist-info/entry_points.txt
harlequin_trino-0.1.6.dist-info/RECORD
