Metadata-Version: 2.1
Name: harlequin_trino
Version: 0.1.6
Summary: A Harlequin adapter for Trino.
Home-page: https://harlequin.sh
License: MIT
Author: Tyler Hillery
Author-email: TylerHillery@users.noreply.github.com
Requires-Python: >=3.10,<4.0
Classifier: License :: OSI Approved :: MIT License
Classifier: Programming Language :: Python :: 3
Classifier: Programming Language :: Python :: 3.10
Classifier: Programming Language :: Python :: 3.11
Requires-Dist: google-auth (>=2.38.0,<3.0.0)
Requires-Dist: harlequin (>=1.7,<3)
Requires-Dist: numpy (>=2.2.4,<3.0.0)
Requires-Dist: trino (>=0.327.0,<0.328.0)
Project-URL: Repository, https://github.com/TylerHillery/harlequin-trino
